setup.py
razmq/__init__.py
razmq.egg-info/PKG-INFO
razmq.egg-info/SOURCES.txt
razmq.egg-info/dependency_links.txt
razmq.egg-info/entry_points.txt
razmq.egg-info/requires.txt
razmq.egg-info/top_level.txt
razmq/backplane/__init__.py
razmq/backplane/backplane.py
razmq/buzzer/__init__.py
razmq/buzzer/buzzer.py
razmq/buzzer/buzzer_pigpio.py
razmq/buzzer/validators/__init__.py
razmq/buzzer/validators/buzzer_test_driver.py
razmq/data_files/lunch/__init__.py
razmq/data_files/lunch/lunchrc.txt
razmq/encoders/__init__.py
razmq/encoders/encoders_pigpio.py
razmq/encoders/validators/__init__.py
razmq/encoders/validators/generate_data_for_gui.py
razmq/gui/__init__.py
razmq/gui/kivy/__init__.py
razmq/gui/kivy/main.py
razmq/gui/kivy/razmqcontrol.kv
razmq/gui/kivy/img/__init__.py
razmq/gui/kivy/img/bline.png
razmq/gui/kivy/img/bline2.png
razmq/gui/kivy/img/bline2_off.png
razmq/gui/kivy/img/bline3.png
razmq/gui/kivy/img/knob_black.png
razmq/gui/kivy/img/knob_metal.png
razmq/gui/kivy/img/ugly_knob.png
razmq/gui/kivy/knob/__init__.py
razmq/gui/remi/__init__.py
razmq/gui/remi/remi_gui.py
razmq/i2c/__init__.py
razmq/i2c/i2c_pigpio.py
razmq/i2c/a2d/__init__.py
razmq/i2c/a2d/i2c_pcf8591.py
razmq/i2c/accelerometers/__init__.py
razmq/i2c/accelerometers/i2c_adxl345.py
razmq/i2c/validators/__init__.py
razmq/i2c/validators/adxl345_disable_tester.py
razmq/i2c/validators/adxl345_enable_tester.py
razmq/i2c/validators/pfc8591_disable_tester.py
razmq/i2c/validators/pfc8591_enable_tester.py
razmq/led/__init__.py
razmq/led/led.py
razmq/led/led_pigpio.py
razmq/led/validators/__init__.py
razmq/led/validators/led_test_driver.py
razmq/motors/__init__.py
razmq/motors/motors.py
razmq/motors/motors_pigpio.py
razmq/motors/validators/__init__.py
razmq/motors/validators/motor_test_driver.py
razmq/razbase/__init__.py
razmq/razbase/razbase.py
razmq/switches/__init__.py
razmq/switches/switches_pigpio.py
razmq/utils/__init__.py
razmq/utils/lunch_config.py
razmq/utils/monitor.py