Metadata-Version: 1.1
Name: razmq
Version: 0.1.1
Summary: A Non-Blocking Event Driven Robotics Framework
Home-page: https://github.com/MrYsLab/razmq
Author: Alan Yorinks
Author-email: MisterYsLab@gmail.com
License: GNU General Public License v3 (GPLv3)
Keywords: Raspberry Pi,ZeroMQ,MessagePack,RedBot
Platform: UNKNOWN
Classifier: Development Status :: 4 - Beta
Classifier: Environment :: Other Environment
Classifier: Intended Audience :: Education
Classifier: License :: OSI Approved :: GNU General Public License v3 or later (GPLv3+)
Classifier: Operating System :: OS Independent
Classifier: Programming Language :: Python :: 3.4
Classifier: Topic :: Education
Classifier: Topic :: Software Development
Classifier: Topic :: Home Automation
Classifier: Topic :: System :: Hardware
